{
  "name": "Quote",
  "preview": "sharepic/templates/fff/preview.jpg",
  "document": "sharepic/templates/fff/document.svg",
  "fonts": [
    {
      "name": "Jost",
      "src": "fonts/jost.ttf",
      "mime": "font/truetype"
    },
    {
      "name": "Merriweather",
      "src": "fonts/Merriweather Sans.ttf",
      "mime": "font/truetype"
    }
  ],
  "fields": [
    {
      "type": "selection",
      "description": "Background",
      "key": "backgroundImage",
      "default": {
        "value": "sharepic/templates/fff/default.jpg",
        "info": {
          "ratio": 1
        }
      },
      "properties": {
        "items": [
          {
            "type": "value",
            "value": "#1DA64A",
            "render": "data:image/svg+xml;base64,PHN2ZyB4bWxucz0iaHR0cDovL3d3dy53My5vcmcvMjAwMC9zdmciIHdpZHRoPSIxMDAlIiBoZWlnaHQ9IjEwMCUiPjxyZWN0IHg9IjAiIHk9IjAiIHdpZHRoPSIxMDAlIiBoZWlnaHQ9IjEwMCUiIGZpbGw9IiMxREE2NEEiLz48L3N2Zz4="
          },
          {
            "type": "value",
            "value": "#1B7340",
            "render": "data:image/svg+xml;base64,PHN2ZyB4bWxucz0iaHR0cDovL3d3dy53My5vcmcvMjAwMC9zdmciIHdpZHRoPSIxMDAlIiBoZWlnaHQ9IjEwMCUiPjxyZWN0IHg9IjAiIHk9IjAiIHdpZHRoPSIxMDAlIiBoZWlnaHQ9IjEwMCUiIGZpbGw9IiMxQjczNDAiLz48L3N2Zz4="
          },
          {
            "type": "file"
          }
        ]
      }
    },
    {
      "type": "selection",
      "description": "Text Background",
      "key": "textBg",
      "default": "#1B7340",
      "properties": {
        "items": [
          {
            "type": "value",
            "value": "#1B7340",
            "render": "data:image/svg+xml;base64,PHN2ZyB4bWxucz0iaHR0cDovL3d3dy53My5vcmcvMjAwMC9zdmciIHdpZHRoPSIxMDAlIiBoZWlnaHQ9IjEwMCUiPjxyZWN0IHg9IjAiIHk9IjAiIHdpZHRoPSIxMDAlIiBoZWlnaHQ9IjEwMCUiIGZpbGw9IiMxQjczNDAiLz48L3N2Zz4="
          },
          {
            "type": "value",
            "value": "#1DA64A",
            "render": "data:image/svg+xml;base64,PHN2ZyB4bWxucz0iaHR0cDovL3d3dy53My5vcmcvMjAwMC9zdmciIHdpZHRoPSIxMDAlIiBoZWlnaHQ9IjEwMCUiPjxyZWN0IHg9IjAiIHk9IjAiIHdpZHRoPSIxMDAlIiBoZWlnaHQ9IjEwMCUiIGZpbGw9IiMxREE2NEEiLz48L3N2Zz4="
          }
        ]
      }
    },
    {
      "type": "number",
      "description": "Position",
      "key": "pos",
      "default": 0,
      "properties": {
        "value": 0,
        "max": 100,
        "min": 0,
        "kind": "slider"
      }
    },
    {
      "type": "number",
      "description": "Opacity",
      "key": "opacity",
      "default": 0.85,
      "properties": {
        "value": 0.85,
        "max": 1,
        "min": 0,
        "kind": "slider",
        "step": 0.01
      }
    },
    {
      "type": "text",
      "description": "Title",
      "key": "title",
      "default": ["WIR STREIKEN", "BIS IHR", "HANDELT!"],
      "properties": {

      }
    },
    {
      "type": "text",
      "description": "Subtitle",
      "key": "subtitle",
      "default": ["“Warum für eine Zukunft", "lernen die es nicht", "mehr geben wird?”"]
    },
    {
      "type": "selection",
      "description": "Logo",
      "key": "logo",
      "properties": {
        "items": [
          {
            "type": "value",
            "value": "sharepic/resources/logo.svg"
          },
          {
            "type": "value",
            "value": "sharepic/resources/logo-2.svg"
          },
          {
            "type": "value",
            "value": "sharepic/resources/logo-3.svg"
          },
          {
            "type": "file"
          }
        ]
      }
    }
  ]
}
